wyc.py
wyc-1.1.0.dist-info/LICENSE
wyc-1.1.0.dist-info/WHEEL
wyc-1.1.0.dist-info/METADATA
wyc-1.1.0.dist-info/RECORD
