Metadata-Version: 2.1
Name: wyc
Version: 1.1.0
Summary: Create WebComponent (Custom Element) from a python file
Home-page: https://github.com/manatlan/wyc
License: MIT
Keywords: web component,custom element,es5,javascript,web,html,es2015,template,transpile
Author: manatlan
Author-email: manatlan@gmail.com
Requires-Python: >=2.7, !=3.0.*, !=3.1.*, !=3.2.*, !=3.3.*, !=3.4.*, !=3.5.*
Classifier: License :: OSI Approved :: MIT License
Classifier: Programming Language :: Python :: 2
Classifier: Programming Language :: Python :: 2.7
Classifier: Programming Language :: Python :: 3
Classifier: Programming Language :: Python :: 3.6
Classifier: Programming Language :: Python :: 3.7
Classifier: Programming Language :: Python :: 3.8
Classifier: Topic :: Software Development :: Build Tools
Classifier: Topic :: Software Development :: Libraries :: Python Modules
Requires-Dist: pscript (>=0.7.0,<0.8.0)
Project-URL: Documentation, https://github.com/manatlan/wyc
Project-URL: Repository, https://github.com/manatlan/wyc
